svmbir-0.4.0.dist-info/RECORD
svmbir-0.4.0.dist-info/LICENSE
svmbir-0.4.0.dist-info/WHEEL
svmbir-0.4.0.dist-info/top_level.txt
svmbir-0.4.0.dist-info/METADATA
svmbir/phantom.py
svmbir/svmbir.py
svmbir/interface_cy_c.cpython-39-darwin.so
svmbir/interface_py_c.py
svmbir/__init__.py
svmbir/_utils.py
svmbir/.dylibs/libgcc_s.1.dylib
svmbir/.dylibs/libgomp.1.dylib
