Metadata-Version: 2.1
Name: svmbir
Version: 0.4.0
Summary: Python code for fast parallel-beam MBIR (Model Based Iterative Reconstruction) 
Home-page: https://github.com/cabouman/svmbir
Maintainer: Charles A. Bouman
Maintainer-email: charles.bouman@gmail.edu
License: BSD-3-Clause
License-File: LICENSE
Requires-Dist: numpy >=1.26.0
Requires-Dist: psutil >=5.8
Requires-Dist: Pillow <=10.1.0
